ghmd/__init__.py
ghmd/__main__.py
ghmd/shared/md-template.html
ghmd/shared/strings.json
ghmd-1.0.1.post1.dist-info/METADATA
ghmd-1.0.1.post1.dist-info/WHEEL
ghmd-1.0.1.post1.dist-info/entry_points.txt
ghmd-1.0.1.post1.dist-info/top_level.txt
ghmd-1.0.1.post1.dist-info/RECORD
