Metadata-Version: 2.4
Name: ghmd
Version: 1.0.1.post1
Summary: A simple CLI to convert markdown files to HTML using GitHub API using the GitHub Markdown style.
Author-email: Román Via-Dufrese Saus <roman910dev@gmail.com>
License-Expression: MIT
Project-URL: Homepage, https://github.com/roman910dev/ghmd
Project-URL: Repository, https://github.com/roman910dev/ghmd.git
Project-URL: Changelog, https://github.com/roman910dev/ghmd/releases
Keywords: markdown,github,cli,html,converter
Classifier: Intended Audience :: End Users/Desktop
Classifier: Intended Audience :: Developers
Classifier: Topic :: Software Development :: Build Tools
Classifier: Topic :: Text Processing :: Markup :: HTML
Classifier: Programming Language :: Python
Classifier: Programming Language :: Python :: 3
Classifier: Programming Language :: Python :: 3.6
Classifier: Programming Language :: Python :: 3.7
Classifier: Programming Language :: Python :: 3.8
Classifier: Programming Language :: Python :: 3.9
Classifier: Programming Language :: Python :: 3.10
Classifier: Programming Language :: Python :: 3.11
Classifier: Programming Language :: Python :: 3.12
Classifier: Programming Language :: Python :: 3.13
Classifier: Programming Language :: Python :: 3.14
Requires-Python: >=3.6
Requires-Dist: requests
